<annotation><folder>train</folder><filename>10e1fb0e8.jpg</filename><size><width>1024</width><height>1024</height><depth>3</depth></size><object><name>wheat head</name><pose>Unspecified</pose><truncated>0</truncated><difficult>0</difficult><bndbox><xmin>491</xmin><ymin>506</ymin><xmax>568</xmax><ymax>604</ymax></bndbox></object><folder>train</folder><filename>10e1fb0e8.jpg</filename><size><width>1024</width><height>1024</height><depth>3</depth></size><object><name>wheat head</name><pose>Unspecified</pose><truncated>0</truncated><difficult>0</difficult><bndbox><xmin>599</xmin><ymin>809</ymin><xmax>693</xmax><ymax>885</ymax></bndbox></object><folder>train</folder><filename>10e1fb0e8.jpg</filename><size><width>1024</width><height>1024</height><depth>3</depth></size><object><name>wheat head</name><pose>Unspecified</pose><truncated>0</truncated><difficult>0</difficult><bndbox><xmin>407</xmin><ymin>455</ymin><xmax>483</xmax><ymax>537</ymax></bndbox></object><folder>train</folder><filename>10e1fb0e8.jpg</filename><size><width>1024</width><height>1024</height><depth>3</depth></size><object><name>wheat head</name><pose>Unspecified</pose><truncated>0</truncated><difficult>0</difficult><bndbox><xmin>926</xmin><ymin>5</ymin><xmax>1016</xmax><ymax>97</ymax></bndbox></object><folder>train</folder><filename>10e1fb0e8.jpg</filename><size><width>1024</width><height>1024</height><depth>3</depth></size><object><name>wheat head</name><pose>Unspecified</pose><truncated>0</truncated><difficult>0</difficult><bndbox><xmin>611</xmin><ymin>99</ymin><xmax>693</xmax><ymax>212</ymax></bndbox></object><folder>train</folder><filename>10e1fb0e8.jpg</filename><size><width>1024</width><height>1024</height><depth>3</depth></size><object><name>wheat head</name><pose>Unspecified</pose><truncated>0</truncated><difficult>0</difficult><bndbox><xmin>1</xmin><ymin>504</ymin><xmax>79</xmax><ymax>569</ymax></bndbox></object><folder>train</folder><filename>10e1fb0e8.jpg</filename><size><width>1024</width><height>1024</height><depth>3</depth></size><object><name>wheat head</name><pose>Unspecified</pose><truncated>0</truncated><difficult>0</difficult><bndbox><xmin>514</xmin><ymin>10</ymin><xmax>599</xmax><ymax>138</ymax></bndbox></object><folder>train</folder><filename>10e1fb0e8.jpg</filename><size><width>1024</width><height>1024</height><depth>3</depth></size><object><name>wheat head</name><pose>Unspecified</pose><truncated>0</truncated><difficult>0</difficult><bndbox><xmin>917</xmin><ymin>616</ymin><xmax>986</xmax><ymax>695</ymax></bndbox></object><folder>train</folder><filename>10e1fb0e8.jpg</filename><size><width>1024</width><height>1024</height><depth>3</depth></size><object><name>wheat head</name><pose>Unspecified</pose><truncated>0</truncated><difficult>0</difficult><bndbox><xmin>768</xmin><ymin>619</ymin><xmax>844</xmax><ymax>691</ymax></bndbox></object><folder>train</folder><filename>10e1fb0e8.jpg</filename><size><width>1024</width><height>1024</height><depth>3</depth></size><object><name>wheat head</name><pose>Unspecified</pose><truncated>0</truncated><difficult>0</difficult><bndbox><xmin>424</xmin><ymin>202</ymin><xmax>568</xmax><ymax>340</ymax></bndbox></object><folder>train</folder><filename>10e1fb0e8.jpg</filename><size><width>1024</width><height>1024</height><depth>3</depth></size><object><name>wheat head</name><pose>Unspecified</pose><truncated>0</truncated><difficult>0</difficult><bndbox><xmin>465</xmin><ymin>394</ymin><xmax>542</xmax><ymax>468</ymax></bndbox></object><folder>train</folder><filename>10e1fb0e8.jpg</filename><size><width>1024</width><height>1024</height><depth>3</depth></size><object><name>wheat head</name><pose>Unspecified</pose><truncated>0</truncated><difficult>0</difficult><bndbox><xmin>907</xmin><ymin>334</ymin><xmax>992</xmax><ymax>468</ymax></bndbox></object><folder>train</folder><filename>10e1fb0e8.jpg</filename><size><width>1024</width><height>1024</height><depth>3</depth></size><object><name>wheat head</name><pose>Unspecified</pose><truncated>0</truncated><difficult>0</difficult><bndbox><xmin>678</xmin><ymin>325</ymin><xmax>755</xmax><ymax>401</ymax></bndbox></object><folder>train</folder><filename>10e1fb0e8.jpg</filename><size><width>1024</width><height>1024</height><depth>3</depth></size><object><name>wheat head</name><pose>Unspecified</pose><truncated>0</truncated><difficult>0</difficult><bndbox><xmin>925</xmin><ymin>717</ymin><xmax>985</xmax><ymax>772</ymax></bndbox></object><folder>train</folder><filename>10e1fb0e8.jpg</filename><size><width>1024</width><height>1024</height><depth>3</depth></size><object><name>wheat head</name><pose>Unspecified</pose><truncated>0</truncated><difficult>0</difficult><bndbox><xmin>931</xmin><ymin>89</ymin><xmax>1024</xmax><ymax>194</ymax></bndbox></object><folder>train</folder><filename>10e1fb0e8.jpg</filename><size><width>1024</width><height>1024</height><depth>3</depth></size><object><name>wheat head</name><pose>Unspecified</pose><truncated>0</truncated><difficult>0</difficult><bndbox><xmin>391</xmin><ymin>135</ymin><xmax>476</xmax><ymax>225</ymax></bndbox></object><folder>train</folder><filename>10e1fb0e8.jpg</filename><size><width>1024</width><height>1024</height><depth>3</depth></size><object><name>wheat head</name><pose>Unspecified</pose><truncated>0</truncated><difficult>0</difficult><bndbox><xmin>609</xmin><ymin>307</ymin><xmax>691</xmax><ymax>384</ymax></bndbox></object><folder>train</folder><filename>10e1fb0e8.jpg</filename><size><width>1024</width><height>1024</height><depth>3</depth></size><object><name>wheat head</name><pose>Unspecified</pose><truncated>0</truncated><difficult>0</difficult><bndbox><xmin>626</xmin><ymin>0</ymin><xmax>685</xmax><ymax>44</ymax></bndbox></object><folder>train</folder><filename>10e1fb0e8.jpg</filename><size><width>1024</width><height>1024</height><depth>3</depth></size><object><name>wheat head</name><pose>Unspecified</pose><truncated>0</truncated><difficult>0</difficult><bndbox><xmin>765</xmin><ymin>529</ymin><xmax>844</xmax><ymax>606</ymax></bndbox></object><folder>train</folder><filename>10e1fb0e8.jpg</filename><size><width>1024</width><height>1024</height><depth>3</depth></size><object><name>wheat head</name><pose>Unspecified</pose><truncated>0</truncated><difficult>0</difficult><bndbox><xmin>742</xmin><ymin>698</ymin><xmax>824</xmax><ymax>778</ymax></bndbox></object><folder>train</folder><filename>10e1fb0e8.jpg</filename><size><width>1024</width><height>1024</height><depth>3</depth></size><object><name>wheat head</name><pose>Unspecified</pose><truncated>0</truncated><difficult>0</difficult><bndbox><xmin>663</xmin><ymin>220</ymin><xmax>732</xmax><ymax>296</ymax></bndbox></object><folder>train</folder><filename>10e1fb0e8.jpg</filename><size><width>1024</width><height>1024</height><depth>3</depth></size><object><name>wheat head</name><pose>Unspecified</pose><truncated>0</truncated><difficult>0</difficult><bndbox><xmin>839</xmin><ymin>834</ymin><xmax>947</xmax><ymax>919</ymax></bndbox></object><folder>train</folder><filename>10e1fb0e8.jpg</filename><size><width>1024</width><height>1024</height><depth>3</depth></size><object><name>wheat head</name><pose>Unspecified</pose><truncated>0</truncated><difficult>0</difficult><bndbox><xmin>275</xmin><ymin>217</ymin><xmax>360</xmax><ymax>290</ymax></bndbox></object><folder>train</folder><filename>10e1fb0e8.jpg</filename><size><width>1024</width><height>1024</height><depth>3</depth></size><object><name>wheat head</name><pose>Unspecified</pose><truncated>0</truncated><difficult>0</difficult><bndbox><xmin>580</xmin><ymin>948</ymin><xmax>635</xmax><ymax>1012</ymax></bndbox></object><folder>train</folder><filename>10e1fb0e8.jpg</filename><size><width>1024</width><height>1024</height><depth>3</depth></size><object><name>wheat head</name><pose>Unspecified</pose><truncated>0</truncated><difficult>0</difficult><bndbox><xmin>646</xmin><ymin>984</ymin><xmax>713</xmax><ymax>1024</ymax></bndbox></object><folder>train</folder><filename>10e1fb0e8.jpg</filename><size><width>1024</width><height>1024</height><depth>3</depth></size><object><name>wheat head</name><pose>Unspecified</pose><truncated>0</truncated><difficult>0</difficult><bndbox><xmin>731</xmin><ymin>794</ymin><xmax>796</xmax><ymax>859</ymax></bndbox></object><folder>train</folder><filename>10e1fb0e8.jpg</filename><size><width>1024</width><height>1024</height><depth>3</depth></size><object><name>wheat head</name><pose>Unspecified</pose><truncated>0</truncated><difficult>0</difficult><bndbox><xmin>971</xmin><ymin>686</ymin><xmax>1024</xmax><ymax>763</ymax></bndbox></object><folder>train</folder><filename>10e1fb0e8.jpg</filename><size><width>1024</width><height>1024</height><depth>3</depth></size><object><name>wheat head</name><pose>Unspecified</pose><truncated>0</truncated><difficult>0</difficult><bndbox><xmin>829</xmin><ymin>778</ymin><xmax>903</xmax><ymax>844</ymax></bndbox></object><folder>train</folder><filename>10e1fb0e8.jpg</filename><size><width>1024</width><height>1024</height><depth>3</depth></size><object><name>wheat head</name><pose>Unspecified</pose><truncated>0</truncated><difficult>0</difficult><bndbox><xmin>80</xmin><ymin>5</ymin><xmax>125</xmax><ymax>108</ymax></bndbox></object></annotation>