<annotation><folder>train</folder><filename>2391f283f.jpg</filename><size><width>1024</width><height>1024</height><depth>3</depth></size><object><name>wheat head</name><pose>Unspecified</pose><truncated>0</truncated><difficult>0</difficult><bndbox><xmin>724</xmin><ymin>371</ymin><xmax>849</xmax><ymax>442</ymax></bndbox></object><folder>train</folder><filename>2391f283f.jpg</filename><size><width>1024</width><height>1024</height><depth>3</depth></size><object><name>wheat head</name><pose>Unspecified</pose><truncated>0</truncated><difficult>0</difficult><bndbox><xmin>0</xmin><ymin>491</ymin><xmax>84</xmax><ymax>576</ymax></bndbox></object><folder>train</folder><filename>2391f283f.jpg</filename><size><width>1024</width><height>1024</height><depth>3</depth></size><object><name>wheat head</name><pose>Unspecified</pose><truncated>0</truncated><difficult>0</difficult><bndbox><xmin>851</xmin><ymin>833</ymin><xmax>1024</xmax><ymax>1015</ymax></bndbox></object><folder>train</folder><filename>2391f283f.jpg</filename><size><width>1024</width><height>1024</height><depth>3</depth></size><object><name>wheat head</name><pose>Unspecified</pose><truncated>0</truncated><difficult>0</difficult><bndbox><xmin>512</xmin><ymin>771</ymin><xmax>581</xmax><ymax>858</ymax></bndbox></object><folder>train</folder><filename>2391f283f.jpg</filename><size><width>1024</width><height>1024</height><depth>3</depth></size><object><name>wheat head</name><pose>Unspecified</pose><truncated>0</truncated><difficult>0</difficult><bndbox><xmin>85</xmin><ymin>68</ymin><xmax>198</xmax><ymax>175</ymax></bndbox></object><folder>train</folder><filename>2391f283f.jpg</filename><size><width>1024</width><height>1024</height><depth>3</depth></size><object><name>wheat head</name><pose>Unspecified</pose><truncated>0</truncated><difficult>0</difficult><bndbox><xmin>952</xmin><ymin>463</ymin><xmax>1024</xmax><ymax>541</ymax></bndbox></object><folder>train</folder><filename>2391f283f.jpg</filename><size><width>1024</width><height>1024</height><depth>3</depth></size><object><name>wheat head</name><pose>Unspecified</pose><truncated>0</truncated><difficult>0</difficult><bndbox><xmin>752</xmin><ymin>518</ymin><xmax>857</xmax><ymax>587</ymax></bndbox></object><folder>train</folder><filename>2391f283f.jpg</filename><size><width>1024</width><height>1024</height><depth>3</depth></size><object><name>wheat head</name><pose>Unspecified</pose><truncated>0</truncated><difficult>0</difficult><bndbox><xmin>0</xmin><ymin>258</ymin><xmax>62</xmax><ymax>380</ymax></bndbox></object><folder>train</folder><filename>2391f283f.jpg</filename><size><width>1024</width><height>1024</height><depth>3</depth></size><object><name>wheat head</name><pose>Unspecified</pose><truncated>0</truncated><difficult>0</difficult><bndbox><xmin>852</xmin><ymin>663</ymin><xmax>980</xmax><ymax>755</ymax></bndbox></object><folder>train</folder><filename>2391f283f.jpg</filename><size><width>1024</width><height>1024</height><depth>3</depth></size><object><name>wheat head</name><pose>Unspecified</pose><truncated>0</truncated><difficult>0</difficult><bndbox><xmin>48</xmin><ymin>0</ymin><xmax>164</xmax><ymax>61</ymax></bndbox></object><folder>train</folder><filename>2391f283f.jpg</filename><size><width>1024</width><height>1024</height><depth>3</depth></size><object><name>wheat head</name><pose>Unspecified</pose><truncated>0</truncated><difficult>0</difficult><bndbox><xmin>921</xmin><ymin>376</ymin><xmax>1024</xmax><ymax>453</ymax></bndbox></object><folder>train</folder><filename>2391f283f.jpg</filename><size><width>1024</width><height>1024</height><depth>3</depth></size><object><name>wheat head</name><pose>Unspecified</pose><truncated>0</truncated><difficult>0</difficult><bndbox><xmin>578</xmin><ymin>611</ymin><xmax>645</xmax><ymax>706</ymax></bndbox></object><folder>train</folder><filename>2391f283f.jpg</filename><size><width>1024</width><height>1024</height><depth>3</depth></size><object><name>wheat head</name><pose>Unspecified</pose><truncated>0</truncated><difficult>0</difficult><bndbox><xmin>931</xmin><ymin>582</ymin><xmax>1024</xmax><ymax>658</ymax></bndbox></object><folder>train</folder><filename>2391f283f.jpg</filename><size><width>1024</width><height>1024</height><depth>3</depth></size><object><name>wheat head</name><pose>Unspecified</pose><truncated>0</truncated><difficult>0</difficult><bndbox><xmin>729</xmin><ymin>915</ymin><xmax>833</xmax><ymax>1015</ymax></bndbox></object><folder>train</folder><filename>2391f283f.jpg</filename><size><width>1024</width><height>1024</height><depth>3</depth></size><object><name>wheat head</name><pose>Unspecified</pose><truncated>0</truncated><difficult>0</difficult><bndbox><xmin>872</xmin><ymin>409</ymin><xmax>972</xmax><ymax>491</ymax></bndbox></object><folder>train</folder><filename>2391f283f.jpg</filename><size><width>1024</width><height>1024</height><depth>3</depth></size><object><name>wheat head</name><pose>Unspecified</pose><truncated>0</truncated><difficult>0</difficult><bndbox><xmin>682</xmin><ymin>444</ymin><xmax>759</xmax><ymax>530</ymax></bndbox></object><folder>train</folder><filename>2391f283f.jpg</filename><size><width>1024</width><height>1024</height><depth>3</depth></size><object><name>wheat head</name><pose>Unspecified</pose><truncated>0</truncated><difficult>0</difficult><bndbox><xmin>493</xmin><ymin>941</ymin><xmax>587</xmax><ymax>1024</ymax></bndbox></object><folder>train</folder><filename>2391f283f.jpg</filename><size><width>1024</width><height>1024</height><depth>3</depth></size><object><name>wheat head</name><pose>Unspecified</pose><truncated>0</truncated><difficult>0</difficult><bndbox><xmin>840</xmin><ymin>850</ymin><xmax>1019</xmax><ymax>946</ymax></bndbox></object><folder>train</folder><filename>2391f283f.jpg</filename><size><width>1024</width><height>1024</height><depth>3</depth></size><object><name>wheat head</name><pose>Unspecified</pose><truncated>0</truncated><difficult>0</difficult><bndbox><xmin>982</xmin><ymin>313</ymin><xmax>1024</xmax><ymax>379</ymax></bndbox></object></annotation>